btcvol_submit.py
btcvol_cli-1.2.0.dist-info/licenses/LICENSE
btcvol_cli-1.2.0.dist-info/METADATA
btcvol_cli-1.2.0.dist-info/WHEEL
btcvol_cli-1.2.0.dist-info/entry_points.txt
btcvol_cli-1.2.0.dist-info/top_level.txt
btcvol_cli-1.2.0.dist-info/RECORD
