Metadata-Version: 2.4
Name: btcvol-cli
Version: 1.2.0
Summary: CLI tool for submitting Bitcoin volatility prediction models to CrunchDAO competitions
Author-email: Jeremy Berros <jberrospellenc@gmail.com>
License-Expression: MIT
Project-URL: Homepage, https://github.com/jberros/btcvol-cli
Project-URL: Documentation, https://github.com/jberros/btcvol-cli#readme
Project-URL: Repository, https://github.com/jberros/btcvol-cli
Project-URL: Issues, https://github.com/jberros/btcvol-cli/issues
Project-URL: Package, https://pypi.org/project/btcvol/
Project-URL: Competition, https://www.crunchdao.com/
Keywords: bitcoin,volatility,prediction,competition,cli,crunchdao
Classifier: Development Status :: 4 - Beta
Classifier: Intended Audience :: Science/Research
Classifier: Topic :: Scientific/Engineering :: Artificial Intelligence
Classifier: Programming Language :: Python :: 3
Classifier: Programming Language :: Python :: 3.9
Classifier: Programming Language :: Python :: 3.10
Classifier: Programming Language :: Python :: 3.11
Classifier: Programming Language :: Python :: 3.12
Requires-Python: >=3.9
License-File: LICENSE
Requires-Dist: pyyaml>=6.0
Dynamic: license-file
